[
  {
    "ContainingType": "WAD.BACKEND._00016180.Controllers.CategoryController",
    "Method": "Create",
    "RelativePath": "api/Category/Create",
    "HttpMethod": "POST",
    "IsController": true,
    "Order": 0,
    "Parameters": [
      {
        "Name": "categories",
        "Type": "WAD.BACKEND._00016180.Models.Category",
        "IsRequired": true
      }
    ],
    "ReturnTypes": []
  },
  {
    "ContainingType": "WAD.BACKEND._00016180.Controllers.CategoryController",
    "Method": "Delete",
    "RelativePath": "api/Category/Delete/{id}",
    "HttpMethod": "DELETE",
    "IsController": true,
    "Order": 0,
    "Parameters": [
      {
        "Name": "id",
        "Type": "System.Int32",
        "IsRequired": true
      }
    ],
    "ReturnTypes": []
  },
  {
    "ContainingType": "WAD.BACKEND._00016180.Controllers.CategoryController",
    "Method": "GetAll",
    "RelativePath": "api/Category/GetAll",
    "HttpMethod": "GET",
    "IsController": true,
    "Order": 0,
    "Parameters": [],
    "ReturnTypes": [
      {
        "Type": "System.Collections.Generic.IEnumerable\u00601[[WAD.BACKEND._00016180.Models.Category, WAD.BACKEND.00016180, Version=1.0.0.0, Culture=neutral, PublicKeyToken=null]]",
        "MediaTypes": [
          "text/plain",
          "application/json",
          "text/json"
        ],
        "StatusCode": 200
      }
    ]
  },
  {
    "ContainingType": "WAD.BACKEND._00016180.Controllers.CategoryController",
    "Method": "GetById",
    "RelativePath": "api/Category/GetById/{id}",
    "HttpMethod": "GET",
    "IsController": true,
    "Order": 0,
    "Parameters": [
      {
        "Name": "id",
        "Type": "System.Int32",
        "IsRequired": true
      }
    ],
    "ReturnTypes": []
  },
  {
    "ContainingType": "WAD.BACKEND._00016180.Controllers.CategoryController",
    "Method": "Update",
    "RelativePath": "api/Category/Update",
    "HttpMethod": "PUT",
    "IsController": true,
    "Order": 0,
    "Parameters": [
      {
        "Name": "categories",
        "Type": "WAD.BACKEND._00016180.Models.Category",
        "IsRequired": true
      }
    ],
    "ReturnTypes": []
  },
  {
    "ContainingType": "WAD.BACKEND._00016180.Controllers.TaskController",
    "Method": "Create",
    "RelativePath": "api/Task/Create",
    "HttpMethod": "POST",
    "IsController": true,
    "Order": 0,
    "Parameters": [
      {
        "Name": "items",
        "Type": "WAD.BACKEND._00016180.Models.Task",
        "IsRequired": true
      }
    ],
    "ReturnTypes": [
      {
        "Type": "System.Void",
        "MediaTypes": [],
        "StatusCode": 201
      }
    ]
  },
  {
    "ContainingType": "WAD.BACKEND._00016180.Controllers.TaskController",
    "Method": "Delete",
    "RelativePath": "api/Task/Delete/{id}",
    "HttpMethod": "DELETE",
    "IsController": true,
    "Order": 0,
    "Parameters": [
      {
        "Name": "id",
        "Type": "System.Int32",
        "IsRequired": true
      }
    ],
    "ReturnTypes": [
      {
        "Type": "System.Void",
        "MediaTypes": [],
        "StatusCode": 204
      },
      {
        "Type": "Microsoft.AspNetCore.Mvc.ProblemDetails",
        "MediaTypes": [
          "text/plain",
          "application/json",
          "text/json"
        ],
        "StatusCode": 404
      }
    ]
  },
  {
    "ContainingType": "WAD.BACKEND._00016180.Controllers.TaskController",
    "Method": "GetAll",
    "RelativePath": "api/Task/GetAll",
    "HttpMethod": "GET",
    "IsController": true,
    "Order": 0,
    "Parameters": [],
    "ReturnTypes": [
      {
        "Type": "System.Collections.Generic.IEnumerable\u00601[[WAD.BACKEND._00016180.Models.Task, WAD.BACKEND.00016180, Version=1.0.0.0, Culture=neutral, PublicKeyToken=null]]",
        "MediaTypes": [
          "text/plain",
          "application/json",
          "text/json"
        ],
        "StatusCode": 200
      }
    ]
  },
  {
    "ContainingType": "WAD.BACKEND._00016180.Controllers.TaskController",
    "Method": "GetById",
    "RelativePath": "api/Task/GetById/{id}",
    "HttpMethod": "GET",
    "IsController": true,
    "Order": 0,
    "Parameters": [
      {
        "Name": "id",
        "Type": "System.Int32",
        "IsRequired": true
      }
    ],
    "ReturnTypes": [
      {
        "Type": "WAD.BACKEND._00016180.Models.Task",
        "MediaTypes": [
          "text/plain",
          "application/json",
          "text/json"
        ],
        "StatusCode": 200
      },
      {
        "Type": "Microsoft.AspNetCore.Mvc.ProblemDetails",
        "MediaTypes": [
          "text/plain",
          "application/json",
          "text/json"
        ],
        "StatusCode": 404
      }
    ]
  },
  {
    "ContainingType": "WAD.BACKEND._00016180.Controllers.TaskController",
    "Method": "Update",
    "RelativePath": "api/Task/Update",
    "HttpMethod": "PUT",
    "IsController": true,
    "Order": 0,
    "Parameters": [
      {
        "Name": "items",
        "Type": "WAD.BACKEND._00016180.Models.Task",
        "IsRequired": true
      }
    ],
    "ReturnTypes": [
      {
        "Type": "System.Void",
        "MediaTypes": [],
        "StatusCode": 204
      },
      {
        "Type": "Microsoft.AspNetCore.Mvc.ProblemDetails",
        "MediaTypes": [
          "text/plain",
          "application/json",
          "text/json"
        ],
        "StatusCode": 400
      }
    ]
  }
]